pyvoronoi.cpython-39-x86_64-linux-gnu.so
pyvoronoi-1.2.4.data/data/pyvoronoi.pyi
pyvoronoi-1.2.4.dist-info/top_level.txt
pyvoronoi-1.2.4.dist-info/RECORD
pyvoronoi-1.2.4.dist-info/METADATA
pyvoronoi-1.2.4.dist-info/WHEEL
