Metadata-Version: 2.4
Name: pyvoronoi
Version: 1.2.4
Summary: Cython wrapper for the Boost Voronoi library (version 1.59.0)
Home-page: https://github.com/fabanc/pyvoronoi
Author: Fabien Ancelin / Andrii Sydorchuk, Voxel8
Author-email: 
Keywords: voronoi,Boost,polygon
Classifier: Programming Language :: Python
Classifier: Programming Language :: Python :: 3
Classifier: Programming Language :: Cython
Classifier: Programming Language :: C++
Classifier: Environment :: Other Environment
Classifier: Development Status :: 5 - Production/Stable
Classifier: Intended Audience :: Developers
Classifier: Operating System :: OS Independent
Classifier: License :: OSI Approved
Classifier: License :: OSI Approved :: MIT License
Classifier: Topic :: Multimedia :: Graphics
Classifier: Topic :: Scientific/Engineering :: Mathematics
Classifier: Topic :: Scientific/Engineering :: GIS
Classifier: Topic :: Software Development :: Libraries :: Python Modules
Requires-Python: >=3.8
Dynamic: author
Dynamic: classifier
Dynamic: description
Dynamic: description-content-type
Dynamic: home-page
Dynamic: keywords
Dynamic: requires-python
Dynamic: summary
